{
  "last_updated": "2026-03-12T21:18:59.234336+00:00",
  "total_alerts": 0,
  "scan_universe": 491,
  "momentum_threshold_pct": 3.0,
  "alerts": [],
  "signals": {
    "top_movers": [],
    "breakouts": [],
    "unusual_volume": [],
    "insider_buying": [],
    "short_squeeze": [],
    "earnings_winners": [],
    "high_revenue_growth": [],
    "institutional_buying": [],
    "rsi_reversals": [],
    "small_cap_momentum": []
  },
  "sector_momentum": [
    {
      "sector": "XLE",
      "weekly_pct": 1.82
    },
    {
      "sector": "XLU",
      "weekly_pct": -0.85
    },
    {
      "sector": "XLP",
      "weekly_pct": -1.36
    },
    {
      "sector": "XLK",
      "weekly_pct": -1.67
    },
    {
      "sector": "XLB",
      "weekly_pct": -2.26
    },
    {
      "sector": "XLV",
      "weekly_pct": -2.44
    },
    {
      "sector": "XLC",
      "weekly_pct": -2.68
    },
    {
      "sector": "XLRE",
      "weekly_pct": -2.77
    },
    {
      "sector": "XLI",
      "weekly_pct": -3.96
    },
    {
      "sector": "XLY",
      "weekly_pct": -4.32
    },
    {
      "sector": "XLF",
      "weekly_pct": -4.68
    }
  ]
}
